LICENSE
MANIFEST.in
README.md
setup.py
sentry_trello/__init__.py
sentry_trello/plugin.py
sentry_trello.egg-info/PKG-INFO
sentry_trello.egg-info/SOURCES.txt
sentry_trello.egg-info/dependency_links.txt
sentry_trello.egg-info/entry_points.txt
sentry_trello.egg-info/requires.txt
sentry_trello.egg-info/top_level.txt