Metadata-Version: 1.0
Name: sentry-trello
Version: 1.0.4
Summary: A Sentry plugin that integrates with Trello
Home-page: https://github.com/DamianZaremba/sentry-trello
Author: Damian Zaremba
Author-email: damian@damianzaremba.co.uk
License: GPL
Platform: UNKNOWN
